{ "_id" : { "$oid" : "51f67b645218297e32e1746c" }, "_created" : { "$date" : 1385621096821 }, "_documentType" : "schema", "_modified" : { "$date" : 1385621096821 }, "_parents" : [ { "$ref" : "group", "$id" : { "$oid" : "4ef31ce1766ec96769b399bd" } } ], "_private" : { "cpe" : [ { "$ref" : "group", "$id" : { "$oid" : "4ef31ce1766ec96769b399bd" } } ] }, "_subtype" : "tv_market", "_version" : 1, "schema" : { "properties" : { "_cm" : { "properties" : { "metadata" : { "properties" : { "clave" : { "description" : "Clave", "required" : true, "type" : "string" }, "creativeAgencyContact" : { "description" : "Creative Agency Contact", "type" : "string" }, "language" : { "description" : "Language", "maxItems" : 1, "name" : "tv_market_spain_language", "type" : "dictionary" }, "mediaAgency" : { "description" : "Media Agency", "type" : "string" }, "mediaAgencyContact" : { "description" : "Media Agency Contact", "type" : "string" }, "subtitlesRequired" : { "description" : "Subtitles Required", "maxItems" : 1, "name" : "tv_market_global_subtitles_required", "type" : "dictionary" } }, "type" : "dynamic_object" } }, "type" : "object" } }, "type" : "object" }, "sv" : 1, "view" : { "properties" : { "_cm" : { "properties" : { "metadata" : { "properties" : { "clave" : { "view" : { "e" : { "order" : 102 }, "v" : { "order" : 102 } } }, "creativeAgencyContact" : { "view" : { "e" : { "order" : 105 }, "v" : { "order" : 105 } } }, "language" : { "view" : { "e" : { "order" : 101 }, "sorted" : true, "v" : { "order" : 101 } } }, "mediaAgency" : { "view" : { "e" : { "order" : 103 }, "v" : { "order" : 103 } } }, "mediaAgencyContact" : { "view" : { "e" : { "order" : 104 }, "v" : { "order" : 104 } } }, "subtitlesRequired" : { "view" : { "defaultValue" : "None", "e" : { "order" : 100 }, "sorted" : true, "v" : { "order" : 100 } } } } } } } } }, "group" : [ "17" ], "name" : "market_schema-17" }
