<UploadJobResponse xmlns:xs="http://adstream.com/xmlstream/" xs:id="22" ns0:type="UploadJobResponse" xmlns:ns0="http://www.w3.org/2001/XMLSchema-instance" xmlns="urn:adstream:yadn">
  <MessageID><![CDATA[1.1|akka://KV01V-A5DA502/user/head/fsobject|54f4f73c8a944662bc7bba3c#1]]></MessageID>
  <Status>UploadedToStorage</Status>
  <FileID>fd9cda59-00a0-4e6e-8fce-a246010d753b</FileID>
  <FileName>ae1af4a3-4606-4f57-8e3e-99452f98ffeb.ods</FileName>
  <FileDirectory><![CDATA[\00000000-0000-0000-0000-000000000000\2013-09-27\54f4f73c8a944662bc7bba3c\]]></FileDirectory>
  <FileSize>7422</FileSize>
  <MD5>0e74d7b8dd41e578e7fe13a72f6ed6a1</MD5>
  <CRC>        </CRC>
  <Node>adstream.yadn.nodes.outpost-a5-auto</Node>
  <SpecDBDocID><![CDATA[f2:application:unspecified:vnd.oasis.opendocument.spreadsheet]]></SpecDBDocID>
  <metadata>
    <property name="isPlayout">
      <Value>false</Value>
    </property>
    <property name="ElementID">
      <Value>54f4f73c8a944662bc7bba3c</Value>
    </property>
    <property name="Path">
      <Value>atCalc03.ods</Value>
    </property>
    <property name="Country">
      <Value>AF</Value>
    </property>
    <property name="guise">
      <Value>master</Value>
    </property>
    <property name="IsPlayout">
      <Value>false</Value>
    </property>
    <property name="evaluation_exiftool">
      <Value><![CDATA[<rdf:RDF xmlns:rdf="http://www.w3.org/1999/02/22-rdf-syntax-ns#">

<rdf:Description xmlns:et="http://ns.exiftool.ca/1.0/" xmlns:ExifTool="http://ns.exiftool.ca/ExifTool/1.0/" xmlns:System="http://ns.exiftool.ca/File/System/1.0/" xmlns:File="http://ns.exiftool.ca/File/1.0/" rdf:about="/media/yadn/input/20130927/509dc6f9cc63477fac2722b6/1380288057677/11b472a0-50f6-4dad-8b13-9b54f4ecf9c6.ods" et:toolkit="Image::ExifTool 8.93">
 <ExifTool:ExifToolVersion>8.93</ExifTool:ExifToolVersion>
 <System:FileName>11b472a0-50f6-4dad-8b13-9b54f4ecf9c6.ods</System:FileName>
 <System:Directory>/media/yadn/input/20130927/509dc6f9cc63477fac2722b6/1380288057677</System:Directory>
 <System:FileSize>7.2 kB</System:FileSize>
 <System:FileModifyDate>2012:12:28 13:04:30+02:00</System:FileModifyDate>
 <System:FilePermissions>rwxrwxrwx</System:FilePermissions>
 <System:FileName>11b472a0-50f6-4dad-8b13-9b54f4ecf9c6.ods</System:FileName>
 <System:Directory>/media/yadn/input/20130927/509dc6f9cc63477fac2722b6/1380288057677</System:Directory>
 <System:FileSize>7.2 kB</System:FileSize>
 <System:FileModifyDate>2012:12:28 13:04:30+02:00</System:FileModifyDate>
 <System:FilePermissions>rwxrwxrwx</System:FilePermissions>
 <File:FileType>ODS</File:FileType>
 <File:MIMEType>application/vnd.oasis.opendocument.spreadsheet</File:MIMEType>
 <File:PreviewPNG>(Binary data 1019 bytes, use -b option to extract)</File:PreviewPNG>
</rdf:Description>
</rdf:RDF>]]></Value>
    </property>
    <property name="evaluation_MediaInfo">
      <Value></Value>
    </property>
    <property name="evaluation_ffprobe">
      <Value></Value>
    </property>
    <property name="evaluation_pdfdimensions">
      <Value></Value>
    </property>
  </metadata>
</UploadJobResponse>